{
	"id": "bf18a85a-9d6f-48e0-9098-27bbf75cd08f",
	"name": "Restful-Booker",
	"values": [
		{
			"key": "dom",
			"value": "https://restful-booker.herokuapp.com",
			"type": "default",
			"enabled": true
		},
		{
			"key": "bookingId",
			"value": "",
			"type": "any",
			"enabled": true
		},
		{
			"key": "authToken",
			"value": "",
			"type": "any",
			"enabled": true
		}
	],
	"_postman_variable_scope": "environment",
	"_postman_exported_at": "2025-08-18T01:20:22.764Z",
	"_postman_exported_using": "Postman/11.58.3"
}